sarscov2summary/__init__.py
sarscov2summary/cli.py
sarscov2summary-0.5.dist-info/LICENSE
sarscov2summary-0.5.dist-info/METADATA
sarscov2summary-0.5.dist-info/WHEEL
sarscov2summary-0.5.dist-info/entry_points.txt
sarscov2summary-0.5.dist-info/top_level.txt
sarscov2summary-0.5.dist-info/RECORD
