Metadata-Version: 2.1
Name: sarscov2summary
Version: 0.5
Summary: Summarizes outputs of Galaxy SARS-CoV2 Selection Analysis workflow
Home-page: https://github.com/nickeener/sarscov2summary
Author: Sergei Pond
Author-email: spond@temple.edu
License: UNKNOWN
Platform: UNKNOWN
Classifier: Programming Language :: Python :: 3
Classifier: License :: OSI Approved :: Academic Free License (AFL)
Classifier: Operating System :: OS Independent
Requires-Python: >=3.6
Requires-Dist: biopython
